pytest_gather_fixtures/__init__.py
pytest_gather_fixtures/_version.py
pytest_gather_fixtures/concurrent_fixture_group.py
pytest_gather_fixtures/topology.py
pytest_gather_fixtures-0.2.1.dist-info/LICENSE
pytest_gather_fixtures-0.2.1.dist-info/METADATA
pytest_gather_fixtures-0.2.1.dist-info/WHEEL
pytest_gather_fixtures-0.2.1.dist-info/RECORD
