Metadata-Version: 2.1
Name: pytest-gather-fixtures
Version: 0.2.1
Summary: set up asynchronous pytest fixtures concurrently
Home-page: https://github.com/bentheiii/pytest-gather-fixtures
License: MIT
Author: Ben Avrahamni
Requires-Python: >=3.8,<4.0
Classifier: License :: OSI Approved :: MIT License
Classifier: Programming Language :: Python :: 3
Classifier: Programming Language :: Python :: 3.8
Classifier: Programming Language :: Python :: 3.9
Classifier: Programming Language :: Python :: 3.10
Classifier: Programming Language :: Python :: 3.11
Classifier: Programming Language :: Python :: 3.12
Requires-Dist: pytest (>=7.0.0)
Requires-Dist: pytest-asyncio (>=0.21.0)
Project-URL: Repository, https://github.com/bentheiii/pytest-gather-fixtures
